geocoder/__init__.py
geocoder/api.py
geocoder/arcgis.py
geocoder/arcgis_reverse.py
geocoder/baidu.py
geocoder/baidu_reverse.py
geocoder/base.py
geocoder/bing.py
geocoder/bing_batch.py
geocoder/bing_batch_forward.py
geocoder/bing_batch_reverse.py
geocoder/bing_reverse.py
geocoder/canadapost.py
geocoder/cli.py
geocoder/distance.py
geocoder/freegeoip.py
geocoder/gaode.py
geocoder/gaode_reverse.py
geocoder/geocodefarm.py
geocoder/geocodefarm_reverse.py
geocoder/geolytica.py
geocoder/geonames.py
geocoder/geonames_children.py
geocoder/geonames_details.py
geocoder/geonames_hierarchy.py
geocoder/gisgraphy.py
geocoder/gisgraphy_reverse.py
geocoder/google.py
geocoder/google_elevation.py
geocoder/google_places.py
geocoder/google_reverse.py
geocoder/google_timezone.py
geocoder/here.py
geocoder/here_reverse.py
geocoder/ipinfo.py
geocoder/keys.py
geocoder/komoot.py
geocoder/komoot_reverse.py
geocoder/location.py
geocoder/locationiq.py
geocoder/locationiq_reverse.py
geocoder/mapbox.py
geocoder/mapbox_reverse.py
geocoder/mapquest.py
geocoder/mapquest_batch.py
geocoder/mapquest_reverse.py
geocoder/mapzen.py
geocoder/mapzen_reverse.py
geocoder/maxmind.py
geocoder/opencage.py
geocoder/opencage_reverse.py
geocoder/osm.py
geocoder/osm_reverse.py
geocoder/ottawa.py
geocoder/ottawa_parcel.py
geocoder/tamu.py
geocoder/tgos.py
geocoder/tomtom.py
geocoder/uscensus.py
geocoder/uscensus_batch.py
geocoder/uscensus_reverse.py
geocoder/w3w.py
geocoder/w3w_reverse.py
geocoder/yahoo.py
geocoder/yandex.py
geocoder/yandex_reverse.py
geocoder-1.38.0.dist-info/DESCRIPTION.rst
geocoder-1.38.0.dist-info/METADATA
geocoder-1.38.0.dist-info/RECORD
geocoder-1.38.0.dist-info/WHEEL
geocoder-1.38.0.dist-info/entry_points.txt
geocoder-1.38.0.dist-info/metadata.json
geocoder-1.38.0.dist-info/top_level.txt
