Metadata-Version: 1.1
Name: geocoder
Version: 1.38.0
Summary: Geocoder is a simple and consistent geocoding library.
Home-page: https://github.com/DenisCarriere/geocoder
Author: Denis Carriere
Author-email: carriere.denis@gmail.com
License: The MIT License
Download-URL: https://github.com/DenisCarriere/geocoder
Keywords: geocoder arcgis tomtom opencage google bing here
Platform: UNKNOWN
Classifier: Development Status :: 5 - Production/Stable
Classifier: Intended Audience :: Developers
Classifier: Intended Audience :: Science/Research
Classifier: License :: OSI Approved :: Apache Software License
Classifier: Natural Language :: English
Classifier: Operating System :: OS Independent
Classifier: Programming Language :: Python :: 2.7
Classifier: Programming Language :: Python :: 3.3
Classifier: Programming Language :: Python :: 3.4
Classifier: Programming Language :: Python :: 3.5
Classifier: Topic :: Internet
Classifier: Topic :: Internet :: WWW/HTTP
Classifier: Topic :: Scientific/Engineering :: GIS
Classifier: Topic :: Software Development :: Libraries :: Python Modules
